use_the_force/__init__.py
use_the_force/_logging.py
use_the_force/forceSensor.py
use_the_force/gui/__init__.py
use_the_force/gui/error_ui.py
use_the_force/gui/error_ui.ui
use_the_force/gui/gui.py
use_the_force/gui/main_ui.py
use_the_force/gui/main_ui.ui
use_the_force/main.py
use_the_force/plotting.py
use_the_force-0.2.0.dist-info/WHEEL
use_the_force-0.2.0.dist-info/entry_points.txt
use_the_force-0.2.0.dist-info/METADATA
use_the_force-0.2.0.dist-info/RECORD
