Metadata-Version: 2.3
Name: use-the-force
Version: 0.2.0
Summary: Code for practicum Use the Force at Vrije Universteit Amsterdam.
Author: Pieter van Toorenenburg
Author-email: Pieter van Toorenenburg <p.h.van.toorenenburg@vu.nl>
Classifier: Programming Language :: Python
Classifier: Programming Language :: Python :: 3
Classifier: Programming Language :: Python :: 3 :: Only
Classifier: Programming Language :: Python :: 3.10
Classifier: Programming Language :: Python :: 3.11
Classifier: Programming Language :: Python :: 3.12
Classifier: Programming Language :: Python :: 3.13
Requires-Dist: matplotlib>=3.10.1
Requires-Dist: pyqtgraph>=0.14.0
Requires-Dist: pyserial>=3.5
Requires-Dist: pyside6-essentials>=6.10.1
Requires-Python: >=3.10
Project-URL: Changelog, https://github.com/NatuurkundePracticumAmsterdam/Use-the-Force/blob/main/CHANGELOG.md
Project-URL: Homepage, https://github.com/NatuurkundePracticumAmsterdam/Use-the-Force
Project-URL: Issues, https://github.com/NatuurkundePracticumAmsterdam/Use-the-Force/issues
Project-URL: Repository, https://github.com/NatuurkundePracticumAmsterdam/Use-the-Force
